{
	"backtrace" : 1,
	"backtraceGraph" : 
	{
		"commands" : 
		[
			"add_custom_target"
		],
		"files" : 
		[
			"rapidjson/CMakeLists.txt"
		],
		"nodes" : 
		[
			{
				"file" : 0
			},
			{
				"command" : 0,
				"file" : 0,
				"line" : 166,
				"parent" : 0
			}
		]
	},
	"dependencies" : 
	[
		{
			"id" : "ZERO_CHECK::@6890427a1f51a3e7e1df"
		}
	],
	"id" : "travis_doc::@011c6e949ad600554a44",
	"name" : "travis_doc",
	"paths" : 
	{
		"build" : "rapidjson",
		"source" : "rapidjson"
	},
	"sources" : [],
	"type" : "UTILITY"
}
